tpch_datagen/__init__.py
tpch_datagen/config.py
tpch_datagen/datagen.py
tpch_datagen/logger.py
tpch_datagen/utils.py
tpch_datagen-0.0.8.dist-info/licenses/LICENSE
tpch_datagen-0.0.8.dist-info/METADATA
tpch_datagen-0.0.8.dist-info/WHEEL
tpch_datagen-0.0.8.dist-info/entry_points.txt
tpch_datagen-0.0.8.dist-info/top_level.txt
tpch_datagen-0.0.8.dist-info/RECORD
