Metadata-Version: 2.4
Name: tpch-datagen
Version: 0.0.8
Summary: A package which makes it easy to generate TPC-H data in parallel with DuckDB
Author-email: Philip Moore <philip@gizmodata.com>
License-Expression: Apache-2.0
Project-URL: Homepage, https://github.com/gizmodata/tpch-datagen
Keywords: tpc,tpch,tpc-h,data,generator,datagen
Classifier: Programming Language :: Python
Classifier: Programming Language :: Python :: 3
Requires-Python: >=3.10
License-File: LICENSE
Requires-Dist: click==8.3.*
Requires-Dist: duckdb==1.4.1
Requires-Dist: munch==4.0.*
Requires-Dist: codetiming==1.4.*
Requires-Dist: python-dotenv==1.1.*
Provides-Extra: dev
Requires-Dist: bumpver; extra == "dev"
Requires-Dist: pip-tools; extra == "dev"
Requires-Dist: pytest; extra == "dev"
Dynamic: license-file
